rf_kv_client/__init__.py
rf_kv_client/main.py
rf_kv_client-0.2.2.dist-info/METADATA
rf_kv_client-0.2.2.dist-info/WHEEL
rf_kv_client-0.2.2.dist-info/top_level.txt
rf_kv_client-0.2.2.dist-info/RECORD
