Metadata-Version: 2.1
Name: rf-kv-client
Version: 0.2.2
Summary: RedForester bindings for AcapellaDB
Home-page: https://redforester.com
Author: Red Forester
Author-email: tech@redforester.com
License: MIT
Platform: UNKNOWN
Classifier: Development Status :: 3 - Alpha
Classifier: License :: OSI Approved :: MIT License
Classifier: Programming Language :: Python :: 3.6
Requires-Python: >=3
Requires-Dist: python-dateutil (>=2.7.5)
Requires-Dist: acapelladb (>=0.3.8)
